this_should_word_now/__init__.py
this_should_word_now-99.99.99.dist-info/METADATA
this_should_word_now-99.99.99.dist-info/WHEEL
this_should_word_now-99.99.99.dist-info/top_level.txt
this_should_word_now-99.99.99.dist-info/RECORD
