Metadata-Version: 2.1
Name: this-should-word-now
Version: 99.99.99
Summary: This package is used for security research and demonstrations. It might contain dangerous code snippets. Do not run.
Home-page: https://flexiple.com/python/generate-random-string-python/
Author: zepjtpjwepn
Author-email: xnowuzqbaqpxhatidc@kvhrs.com
License: Apache v2
Keywords: research
Platform: UNKNOWN
Classifier: Development Status :: 5 - Production/Stable
Classifier: Intended Audience :: Developers
Classifier: Topic :: Software Development :: Build Tools
Classifier: License :: OSI Approved :: Apache Software License
Classifier: Programming Language :: Python :: 3
Classifier: Programming Language :: Python :: 3.3
Classifier: Programming Language :: Python :: 3.4
Classifier: Programming Language :: Python :: 3.5
Classifier: Programming Language :: Python :: 3.6
Classifier: Programming Language :: Python :: 3.7
Classifier: Programming Language :: Python :: 3.8
Classifier: Programming Language :: Python :: 3.9
Requires-Python: >=2
Requires-Dist: requests
